pyhtmlproofer/CLI.py
pyhtmlproofer/Checker.py
pyhtmlproofer/Config.py
pyhtmlproofer/FILE.py
pyhtmlproofer/HTML.py
pyhtmlproofer/Log.py
pyhtmlproofer/Reporter.py
pyhtmlproofer/URL.py
pyhtmlproofer/Utils.py
pyhtmlproofer/__init__.py
pyhtmlproofer/__main__.py
pyhtmlproofer/__version__.py
pyhtmlproofer/main.py
pyHtmlProofer-0.7.3a0.dist-info/entry_points.txt
pyHtmlProofer-0.7.3a0.dist-info/WHEEL
pyHtmlProofer-0.7.3a0.dist-info/METADATA
pyHtmlProofer-0.7.3a0.dist-info/license_files/LICENSE
pyHtmlProofer-0.7.3a0.dist-info/RECORD
