Metadata-Version: 2.1
Name: pyHtmlProofer
Version: 0.7.3-alpha
Summary: pyHtmlProofer - A tool for validating internal & external links in HTML files / Websites
License: AGPL-3.0
Author-email: Rehan Haider <email@rehanhaider.com>
Requires-Python: >=3.7
Classifier: Development Status :: 3 - Alpha
Classifier: License :: OSI Approved :: MIT License
Classifier: Operating System :: OS Independent
Classifier: Programming Language :: Python :: 3
Classifier: Programming Language :: Python :: 3.10
Classifier: Programming Language :: Python :: 3.11
Classifier: Programming Language :: Python :: 3.8
Classifier: Programming Language :: Python :: 3.9
Classifier: Topic :: Internet :: WWW/HTTP
Classifier: Topic :: Internet :: WWW/HTTP :: Site Management
Classifier: Topic :: Internet :: WWW/HTTP :: Site Management :: Link Checking
Classifier: Topic :: Software Development :: Libraries :: Python Modules
Classifier: Topic :: Software Development :: Quality Assurance
Classifier: Topic :: Software Development :: Testing
Requires-Dist: beautifulsoup4>=4.11.1
Requires-Dist: html5lib>=1.1
Requires-Dist: lxml>=4.9.1
Requires-Dist: requests>=2.28.1
Requires-Dist: rich>=12.5.1
Project-URL: Source, https://github.com/rehanhaider/pyhtmlproofer
